grid_extractor/__init__.py
grid_extractor/core.py
grid_extractor/api/__init__.py
grid_extractor/api/cv2helper.py
grid_extractor/test/__init__.py
grid_extractor/test/test.py
grid_extractor/test/image/GB18030/no_watermark.jpg
grid_extractor/test/image/GeneralStandardChineseCharacter/pg_045.jpg
grid_extractor/test/image/JIS/jis_x_ch_pg_08.tiff
grid_extractor/test/image/JIS/jis_x_j_pr10_i4_pg_229.tiff
grid_extractor-0.0.2.dist-info/LICENSE
grid_extractor-0.0.2.dist-info/METADATA
grid_extractor-0.0.2.dist-info/WHEEL
grid_extractor-0.0.2.dist-info/entry_points.txt
grid_extractor-0.0.2.dist-info/top_level.txt
grid_extractor-0.0.2.dist-info/zip-safe
grid_extractor-0.0.2.dist-info/RECORD
