Metadata-Version: 2.1
Name: grid-extractor
Version: 0.0.2
Summary: It's a library to help you take out the text from the grid
Home-page: https://github.com/CarsonSlovoka/grid-extractor/tree/master
Author: Carson
Author-email: jackparadise520a@gmail.com
License: BSD 3-Clause
Project-URL: Homepage, https://github.com/CarsonSlovoka/grid-extractor/tree/master
Project-URL: Documentation, https://carsonslovoka.github.io/grid-extractor/en/index.html
Project-URL: Code, https://github.com/CarsonSlovoka/grid-extractor/tree/master
Project-URL: Issue Tracker, https://github.com/CarsonSlovoka/grid-extractor/issues
Project-URL: Download, https://github.com/CarsonSlovoka/grid-extractor/tree/master
Keywords: opencv
Platform: UNKNOWN
Classifier: Development Status :: 3 - Alpha
Classifier: License :: OSI Approved
Classifier: Natural Language :: Chinese (Traditional)
Classifier: Natural Language :: English
Classifier: Operating System :: Microsoft
Classifier: Operating System :: POSIX
Classifier: Operating System :: Unix
Classifier: Operating System :: MacOS
Classifier: Programming Language :: Python :: 3 :: Only
Classifier: Programming Language :: Python :: 3.6
Classifier: Programming Language :: Python :: 3.7
Classifier: Programming Language :: Python :: 3.8
Classifier: Programming Language :: Python :: 3.9
Classifier: Topic :: Scientific/Engineering :: Image Recognition
Requires-Python: >=3.6.2,
Requires-Dist: opencv-python
Requires-Dist: numpy
